socketcan_uds/__init__.py
socketcan_uds/client.py
socketcan_uds/common.py
socketcan_uds/odx_elements.py
socketcan_uds/odx_file_utils.py
socketcan_uds/program_file.py
socketcan_uds/programmer.py
socketcan_uds/security_access.py
socketcan_uds-1.0.0.dist-info/LICENSE
socketcan_uds-1.0.0.dist-info/METADATA
socketcan_uds-1.0.0.dist-info/WHEEL
socketcan_uds-1.0.0.dist-info/top_level.txt
socketcan_uds-1.0.0.dist-info/RECORD
