Metadata-Version: 2.1
Name: socketcan-uds
Version: 1.0.0
Summary: A python 3 interface to Unified Diagnostic Services (UDS) Protocol
Author-email: Patrick Menschel <menschel.p@posteo.de>
Project-URL: Homepage, https://gitlab.com/menschel/socketcan-uds
Project-URL: Bug Tracker, https://gitlab.com/menschel/socketcan-uds/issues
Classifier: Programming Language :: Python :: 3
Classifier: Development Status :: 5 - Production/Stable
Classifier: License :: OSI Approved :: GNU General Public License v3 or later (GPLv3+)
Classifier: License :: Free for non-commercial use
Classifier: Operating System :: POSIX :: Linux
Classifier: Intended Audience :: Developers
Classifier: Topic :: Scientific/Engineering
Classifier: Topic :: Software Development :: Embedded Systems
Requires-Python: >=3.10
License-File: LICENSE
Requires-Dist: socketcan
Provides-Extra: dev
Requires-Dist: build ; extra == 'dev'
Requires-Dist: twine ; extra == 'dev'
Provides-Extra: test
Requires-Dist: pytest ; extra == 'test'
Requires-Dist: pytest-cov ; extra == 'test'
Requires-Dist: tox ; extra == 'test'
